LICENSE.txt
README.md
pyproject.toml
setup.cfg
setup.py
kibbe.egg-info/PKG-INFO
kibbe.egg-info/SOURCES.txt
kibbe.egg-info/dependency_links.txt
kibbe.egg-info/entry_points.txt
kibbe.egg-info/requires.txt
kibbe.egg-info/top_level.txt
src/__init__.py
src/config.py
src/git.py
src/main.py
src/tmux.py
src/util.py
src/commands/__init__.py
src/commands/check.py
src/commands/checkout.py
src/commands/config.py
src/commands/ctx.py
src/commands/es.py
src/commands/fleet.py
src/commands/jest.py
src/commands/kibana.py
src/commands/setlicense.py
src/commands/setmeup.py