Metadata-Version: 1.1
Name: kibbe
Version: 0.51.0
Summary: Collection of commands and helpers to ease kibana development
Home-page: https://github.com/academo/kibbe/
Author: Esteban Beltran
Author-email: kibbe@academo.me
License: UNKNOWN
Download-URL: https://github.com/academo/kibbe/releases
Platform: UNKNOWN
